{
  "_class": "group",
  "booleanOperation": -1,
  "clippingMaskMode": 0,
  "do_objectID": "68E9B137-4ADB-4983-ACC0-042CC71D939D",
  "exportOptions": {
    "_class": "exportOptions",
    "exportFormats": [
    ],
    "includedLayerIds": [
    ],
    "layerOptions": 0,
    "shouldTrim": false
  },
  "frame": {
    "_class": "rect",
    "constrainProportions": false,
    "height": 260,
    "width": 73,
    "x": 51,
    "y": 25
  },
  "hasClickThrough": false,
  "hasClippingMask": false,
  "isFixedToViewport": false,
  "isFlippedHorizontal": false,
  "isFlippedVertical": false,
  "isLocked": false,
  "isVisible": true,
  "layerListExpandedType": 0,
  "layers": [
    {
      "class": "shapeGroup",
      "id": "E1D815E7-E2EA-4D8D-AF24-9C3727D28375"
    },
    {
      "class": "shapeGroup",
      "id": "18772D21-DDEB-4DFE-B397-2305CE392B3F"
    },
    {
      "class": "shapeGroup",
      "id": "7147382D-5E68-4354-88CD-7B05E022BDDE"
    },
    {
      "class": "shapeGroup",
      "id": "D795DF58-60D8-432D-BED7-FD141931D624"
    },
    {
      "class": "shapeGroup",
      "id": "E17A5A1D-45FE-4B01-829B-8BEEE5216140"
    },
    {
      "class": "shapeGroup",
      "id": "B7180C3F-78F3-4062-8986-53FA9BA775BB"
    },
    {
      "class": "shapeGroup",
      "id": "E53C530D-1A31-4F8C-9484-2B279FE4345B"
    },
    {
      "class": "shapeGroup",
      "id": "21947B47-36C1-4EC1-85BF-58E58B82F2CB"
    }
  ],
  "name": "Group 3",
  "nameIsFixed": false,
  "resizingConstraint": 63,
  "resizingType": 0,
  "rotation": 0,
  "shouldBreakMaskChain": false,
  "style": {
    "_class": "style",
    "endMarkerType": 0,
    "miterLimit": 10,
    "startMarkerType": 0,
    "windingRule": 1
  },
  "userInfo": {
    "com.animaapp.stc-sketch-plugin": {
      "kModelPropertiesKey": {
      }
    }
  }
}