{
  "_class": "shapePath",
  "booleanOperation": -1,
  "clippingMaskMode": 0,
  "do_objectID": "F0DE5A57-6660-4CF8-9827-1E8AC0B0D2B4",
  "edited": true,
  "exportOptions": {
    "_class": "exportOptions",
    "exportFormats": [
    ],
    "includedLayerIds": [
    ],
    "layerOptions": 0,
    "shouldTrim": false
  },
  "frame": {
    "_class": "rect",
    "constrainProportions": false,
    "do_objectID": "9CFA256C-DAE5-4CD6-BB7A-326A8FAB0F42",
    "height": 235.441,
    "width": 247.683,
    "x": 78.15899999999999,
    "y": 82.035
  },
  "hasClippingMask": false,
  "isClosed": true,
  "isFixedToViewport": false,
  "isFlippedHorizontal": false,
  "isFlippedVertical": false,
  "isLocked": false,
  "isVisible": true,
  "layerListExpandedType": 0,
  "name": "path-1-path",
  "nameIsFixed": false,
  "pointRadiusBehaviour": 1,
  "points": [
    {
      "_class": "curvePoint",
      "cornerRadius": 0,
      "curveFrom": "{0.56674055143065938, 0.84628845443232059}",
      "curveMode": 1,
      "curveTo": "{0.56674055143065938, 0.84628845443232059}",
      "hasCurveFrom": false,
      "hasCurveTo": false,
      "point": "{0.56674055143065938, 0.84628845443232059}"
    },
    {
      "_class": "curvePoint",
      "cornerRadius": 0,
      "curveFrom": "{0.49999798129060136, 0.80392539956931885}",
      "curveMode": 1,
      "curveTo": "{0.49999798129060136, 0.80392539956931885}",
      "hasCurveFrom": false,
      "hasCurveTo": false,
      "point": "{0.49999798129060136, 0.80392539956931885}"
    },
    {
      "_class": "curvePoint",
      "cornerRadius": 0,
      "curveFrom": "{0.43325944856934068, 0.84628420708372809}",
      "curveMode": 1,
      "curveTo": "{0.43325944856934068, 0.84628420708372809}",
      "hasCurveFrom": false,
      "hasCurveTo": false,
      "point": "{0.43325944856934068, 0.84628420708372809}"
    },
    {
      "_class": "curvePoint",
      "cornerRadius": 0,
      "curveFrom": "{0.19106276975004344, 1}",
      "curveMode": 1,
      "curveTo": "{0.19106276975004344, 1}",
      "hasCurveFrom": false,
      "hasCurveTo": false,
      "point": "{0.19106276975004344, 1}"
    },
    {
      "_class": "curvePoint",
      "cornerRadius": 0,
      "curveFrom": "{0.25517294283418723, 0.70992308051698727}",
      "curveMode": 1,
      "curveTo": "{0.25517294283418723, 0.70992308051698727}",
      "hasCurveFrom": false,
      "hasCurveTo": false,
      "point": "{0.25517294283418723, 0.70992308051698727}"
    },
    {
      "_class": "curvePoint",
      "cornerRadius": 0,
      "curveFrom": "{0.27281242556009094, 0.63011540046126202}",
      "curveMode": 1,
      "curveTo": "{0.27281242556009094, 0.63011540046126202}",
      "hasCurveFrom": false,
      "hasCurveTo": false,
      "point": "{0.27281242556009094, 0.63011540046126202}"
    },
    {
      "_class": "curvePoint",
      "cornerRadius": 0,
      "curveFrom": "{0.21395897175018069, 0.57644165629605715}",
      "curveMode": 1,
      "curveTo": "{0.21395897175018069, 0.57644165629605715}",
      "hasCurveFrom": false,
      "hasCurveTo": false,
      "point": "{0.21395897175018069, 0.57644165629605715}"
    },
    {
      "_class": "curvePoint",
      "cornerRadius": 0,
      "curveFrom": "{0, 0.38132270929872025}",
      "curveMode": 1,
      "curveTo": "{0, 0.38132270929872025}",
      "hasCurveFrom": false,
      "hasCurveTo": false,
      "point": "{0, 0.38132270929872025}"
    },
    {
      "_class": "curvePoint",
      "cornerRadius": 0,
      "curveFrom": "{0.28195717913623469, 0.35584711244005929}",
      "curveMode": 1,
      "curveTo": "{0.28195717913623469, 0.35584711244005929}",
      "hasCurveFrom": false,
      "hasCurveTo": false,
      "point": "{0.28195717913623469, 0.35584711244005929}"
    },
    {
      "_class": "curvePoint",
      "cornerRadius": 0,
      "curveFrom": "{0.35949984455937634, 0.34883898726220158}",
      "curveMode": 1,
      "curveTo": "{0.35949984455937634, 0.34883898726220158}",
      "hasCurveFrom": false,
      "hasCurveTo": false,
      "point": "{0.35949984455937634, 0.34883898726220158}"
    },
    {
      "_class": "curvePoint",
      "cornerRadius": 0,
      "curveFrom": "{0.38986527133473026, 0.27344854974282307}",
      "curveMode": 1,
      "curveTo": "{0.38986527133473026, 0.27344854974282307}",
      "hasCurveFrom": false,
      "hasCurveTo": false,
      "point": "{0.38986527133473026, 0.27344854974282307}"
    },
    {
      "_class": "curvePoint",
      "cornerRadius": 0,
      "curveFrom": "{0.49998990645300645, 0}",
      "curveMode": 1,
      "curveTo": "{0.49998990645300645, 0}",
      "hasCurveFrom": false,
      "hasCurveTo": false,
      "point": "{0.49998990645300645, 0}"
    },
    {
      "_class": "curvePoint",
      "cornerRadius": 0,
      "curveFrom": "{0.61009031705849814, 0.27344005504563773}",
      "curveMode": 1,
      "curveTo": "{0.61009031705849814, 0.27344005504563773}",
      "hasCurveFrom": false,
      "hasCurveTo": false,
      "point": "{0.61009031705849814, 0.27344005504563773}"
    },
    {
      "_class": "curvePoint",
      "cornerRadius": 0,
      "curveFrom": "{0.64045170641505456, 0.34883473991360892}",
      "curveMode": 1,
      "curveTo": "{0.64045170641505456, 0.34883473991360892}",
      "hasCurveFrom": false,
      "hasCurveTo": false,
      "point": "{0.64045170641505456, 0.34883473991360892}"
    },
    {
      "_class": "curvePoint",
      "cornerRadius": 0,
      "curveFrom": "{0.71800244667579116, 0.35584286509146668}",
      "curveMode": 1,
      "curveTo": "{0.71800244667579116, 0.35584286509146668}",
      "hasCurveFrom": false,
      "hasCurveTo": false,
      "point": "{0.71800244667579116, 0.35584286509146668}"
    },
    {
      "_class": "curvePoint",
      "cornerRadius": 0,
      "curveFrom": "{1, 0.38131846195012759}",
      "curveMode": 1,
      "curveTo": "{1, 0.38131846195012759}",
      "hasCurveFrom": false,
      "hasCurveTo": false,
      "point": "{1, 0.38131846195012759}"
    },
    {
      "_class": "curvePoint",
      "cornerRadius": 0,
      "curveFrom": "{0.78604506566861676, 0.57643740894746465}",
      "curveMode": 1,
      "curveTo": "{0.78604506566861676, 0.57643740894746465}",
      "hasCurveFrom": false,
      "hasCurveTo": false,
      "point": "{0.78604506566861676, 0.57643740894746465}"
    },
    {
      "_class": "curvePoint",
      "cornerRadius": 0,
      "curveFrom": "{0.7271956492775038, 0.63010690576407691}",
      "curveMode": 1,
      "curveTo": "{0.7271956492775038, 0.63010690576407691}",
      "hasCurveFrom": false,
      "hasCurveTo": false,
      "point": "{0.7271956492775038, 0.63010690576407691}"
    },
    {
      "_class": "curvePoint",
      "cornerRadius": 0,
      "curveFrom": "{0.74482705716581277, 0.70990609112261693}",
      "curveMode": 1,
      "curveTo": "{0.74482705716581277, 0.70990609112261693}",
      "hasCurveFrom": false,
      "hasCurveTo": false,
      "point": "{0.74482705716581277, 0.70990609112261693}"
    },
    {
      "_class": "curvePoint",
      "cornerRadius": 0,
      "curveFrom": "{0.80892108057476697, 0.9999957526514075}",
      "curveMode": 1,
      "curveTo": "{0.80892108057476697, 0.9999957526514075}",
      "hasCurveFrom": false,
      "hasCurveTo": false,
      "point": "{0.80892108057476697, 0.9999957526514075}"
    }
  ],
  "resizingConstraint": 63,
  "resizingType": 0,
  "rotation": 0,
  "shouldBreakMaskChain": false,
  "style": {
    "_class": "style",
    "do_objectID": "8CF7B091-669C-40CD-A329-D46493D8635D",
    "endMarkerType": 0,
    "fills": [
      {
        "_class": "fill",
        "color": {
          "_class": "color",
          "alpha": 1,
          "blue": 0,
          "green": 0,
          "red": 0
        },
        "fillType": 0,
        "isEnabled": true,
        "noiseIndex": 0,
        "noiseIntensity": 0,
        "patternFillType": 1,
        "patternTileScale": 1
      }
    ],
    "miterLimit": 10,
    "startMarkerType": 0,
    "windingRule": 0
  }
}