{
  "_class": "group",
  "booleanOperation": -1,
  "clippingMaskMode": 0,
  "do_objectID": "C1CFC1C5-3F40-40BF-B68A-FC40A3B38F2B",
  "exportOptions": {
    "_class": "exportOptions",
    "exportFormats": [
    ],
    "includedLayerIds": [
    ],
    "layerOptions": 0,
    "shouldTrim": false
  },
  "frame": {
    "_class": "rect",
    "constrainProportions": false,
    "do_objectID": "FA8170E9-642E-484C-95FC-8709A99FD6F5",
    "height": 619,
    "width": 328,
    "x": 0,
    "y": 454
  },
  "hasClickThrough": false,
  "hasClippingMask": false,
  "isFixedToViewport": false,
  "isFlippedHorizontal": false,
  "isFlippedVertical": false,
  "isLocked": false,
  "isVisible": true,
  "layerListExpandedType": 2,
  "layers": [
    {
      "class": "group",
      "id": "9BDDDEEA-C4E5-44DC-8093-25E489DEB750"
    },
    {
      "class": "text",
      "id": "7260EC1E-825B-4416-9FE7-618AB0D83C01"
    },
    {
      "class": "text",
      "id": "7A677F32-F8BC-47F5-BB9E-2CAD65AB14BA"
    },
    {
      "class": "group",
      "id": "8E6EBFCA-DE6C-468F-BB1B-C375957947E2"
    },
    {
      "class": "text",
      "id": "3CB0100D-12E1-4998-94CE-9154AA01501B"
    }
  ],
  "name": "Sa Symérie",
  "nameIsFixed": true,
  "resizingConstraint": 63,
  "resizingType": 0,
  "rotation": 0,
  "shouldBreakMaskChain": false,
  "style": {
    "_class": "style",
    "do_objectID": "5B8AB2AE-ADFA-4D3F-AA3A-3A9C512A55A4",
    "endMarkerType": 0,
    "miterLimit": 10,
    "startMarkerType": 0,
    "windingRule": 1
  },
  "userInfo": {
    "com.animaapp.stc-sketch-plugin": {
      "kModelPropertiesKey": {
      }
    }
  }
}