{
  "_class": "artboard",
  "backgroundColor": {
    "_class": "color",
    "alpha": 1,
    "blue": 0.9490196078431372,
    "green": 0.9411764705882353,
    "red": 0.9411764705882353
  },
  "booleanOperation": 0,
  "clippingMaskMode": 0,
  "do_objectID": "753F06D2-42EC-438F-8A0E-3EA1ED31EA23",
  "exportOptions": {
    "_class": "exportOptions",
    "exportFormats": [
    ],
    "includedLayerIds": [
    ],
    "layerOptions": 0,
    "shouldTrim": false
  },
  "frame": {
    "_class": "rect",
    "constrainProportions": false,
    "height": 1622,
    "width": 360,
    "x": -15454,
    "y": -11149
  },
  "hasBackgroundColor": true,
  "hasClickThrough": true,
  "hasClippingMask": false,
  "horizontalRulerData": {
    "_class": "rulerData",
    "base": 0,
    "guides": [
    ]
  },
  "includeBackgroundColorInExport": true,
  "includeInCloudUpload": true,
  "isFixedToViewport": false,
  "isFlippedHorizontal": false,
  "isFlippedVertical": false,
  "isFlowHome": false,
  "isLocked": false,
  "isVisible": true,
  "layerListExpandedType": 2,
  "layers": [
    {
      "class": "group",
      "id": "6062218F-38D5-4702-9E28-08FC80DC18DD"
    },
    {
      "class": "oval",
      "id": "A16C4911-B25C-49AC-BC5B-EAC20283EE33"
    },
    {
      "class": "symbolInstance",
      "id": "473E3F74-4E89-4E94-9419-300E9354CD8F"
    },
    {
      "class": "group",
      "id": "794ECBBA-AC76-4CC5-8E7E-1612117DAFD7"
    },
    {
      "class": "symbolInstance",
      "id": "251B99F3-51A8-4092-A88A-B9BDBC6A29E4"
    },
    {
      "class": "group",
      "id": "0A3E74EA-26A4-4B77-A572-1BD3318EAD56"
    },
    {
      "class": "group",
      "id": "DD427DDD-32BF-4DF7-B9EA-4F02E63E7407"
    },
    {
      "class": "group",
      "id": "257DDD1F-369E-495E-8D3F-7D605EAE6166"
    },
    {
      "class": "symbolInstance",
      "id": "C7DF75EB-9F1C-4D50-B47B-ABC0E4581EAB"
    },
    {
      "class": "symbolInstance",
      "id": "9CB67BD1-83A2-48A6-B0F8-CB79263B4780"
    },
    {
      "class": "symbolInstance",
      "id": "60A3A8F7-135C-443F-A0EB-2E5B995EEF93"
    },
    {
      "class": "group",
      "id": "A45E4797-D146-4555-90EB-3866B21E53CD"
    },
    {
      "class": "text",
      "id": "DF8BDBE8-6500-4A74-A440-10653CB5F833"
    },
    {
      "class": "symbolInstance",
      "id": "96F3679C-A8E1-4025-BFEC-2EE34A03F648"
    },
    {
      "class": "symbolInstance",
      "id": "FBE7BF29-9E4F-48F0-A36F-281681CB78BC"
    }
  ],
  "layout": {
    "_class": "layoutGrid",
    "columnWidth": 20,
    "drawHorizontal": false,
    "drawHorizontalLines": false,
    "drawVertical": true,
    "gutterHeight": 12,
    "gutterWidth": 8,
    "guttersOutside": false,
    "horizontalOffset": 16,
    "isEnabled": true,
    "numberOfColumns": 12,
    "rowHeightMultiplication": 5,
    "totalWidth": 328
  },
  "name": "Register/horse/P1 (1)",
  "nameIsFixed": false,
  "presetDictionary": {
    "allowResizedMatching": 0,
    "height": 640,
    "name": "Android",
    "offersLandscapeVariant": 1,
    "width": 360
  },
  "resizesContent": true,
  "resizingConstraint": 63,
  "resizingType": 0,
  "rotation": 0,
  "shouldBreakMaskChain": true,
  "style": {
    "_class": "style",
    "endMarkerType": 0,
    "miterLimit": 10,
    "startMarkerType": 0,
    "windingRule": 1
  },
  "userInfo": {
    "com.animaapp.stc-sketch-plugin": {
      "kModelPropertiesKey": {
      }
    }
  },
  "verticalRulerData": {
    "_class": "rulerData",
    "base": 0,
    "guides": [
    ]
  }
}