{
  "_class": "group",
  "booleanOperation": 0,
  "clippingMaskMode": 0,
  "do_objectID": "F39D7290-4D15-482C-80F8-1269F7B4A0FE",
  "exportOptions": {
    "_class": "exportOptions",
    "exportFormats": [
    ],
    "includedLayerIds": [
    ],
    "layerOptions": 0,
    "shouldTrim": false
  },
  "frame": {
    "_class": "rect",
    "constrainProportions": true,
    "do_objectID": "F10D972C-9937-4F5F-B2F5-E364EF6E6218",
    "height": 408,
    "width": 510,
    "x": 0,
    "y": 0
  },
  "hasClickThrough": false,
  "hasClippingMask": false,
  "isFixedToViewport": false,
  "isFlippedHorizontal": false,
  "isFlippedVertical": false,
  "isLocked": false,
  "isVisible": true,
  "layerListExpandedType": 0,
  "layers": [
    {
      "class": "shapeGroup",
      "id": "7AD36BFB-1E06-41E5-A7BA-BEDEC358C691"
    },
    {
      "class": "group",
      "id": "D586A837-406E-491C-ADEB-76CAFD6924FB"
    }
  ],
  "name": "Calque_1",
  "nameIsFixed": false,
  "resizingConstraint": 63,
  "resizingType": 0,
  "rotation": 0,
  "shouldBreakMaskChain": false,
  "style": {
    "_class": "style",
    "do_objectID": "009B6045-088B-45F5-9423-06E06DF458E6",
    "endMarkerType": 0,
    "fills": [
      {
        "_class": "fill",
        "color": {
          "_class": "color",
          "alpha": 1,
          "blue": 0,
          "green": 0,
          "red": 0
        },
        "fillType": 0,
        "isEnabled": true,
        "noiseIndex": 0,
        "noiseIntensity": 0,
        "patternFillType": 1,
        "patternTileScale": 1
      }
    ],
    "miterLimit": 10,
    "startMarkerType": 0,
    "windingRule": 1
  },
  "userInfo": {
    "com.animaapp.stc-sketch-plugin": {
      "kModelPropertiesKey": {
        "constraints": {
          "aspectRatio": {
            "constant": 356.1348,
            "enabled": 1,
            "modelID": "constraint_a4f9775d-14f4-4542-852a-468da77ce644",
            "model_class": "ADModelConstraint",
            "model_version": 0.1,
            "multiplier": 448
          },
          "automatic": 1,
          "modelID": "viewConstraints_282ed103-d16b-44d0-9ec0-3796f849a96f",
          "model_class": "ADModelViewConstraints",
          "model_version": 0.1,
          "scaleFactor": 1
        }
      }
    }
  }
}