{
  "_class": "symbolMaster",
  "backgroundColor": {
    "_class": "color",
    "alpha": 1,
    "blue": 1,
    "do_objectID": "D18AD6FA-40B2-4E28-9BA7-E91A83B61310",
    "green": 1,
    "red": 1
  },
  "booleanOperation": 0,
  "changeIdentifier": 224,
  "clippingMaskMode": 0,
  "do_objectID": "CE8BC74C-F057-47E6-8284-7E959B21363F",
  "exportOptions": {
    "_class": "exportOptions",
    "exportFormats": [
    ],
    "includedLayerIds": [
    ],
    "layerOptions": 0,
    "shouldTrim": false
  },
  "frame": {
    "_class": "rect",
    "constrainProportions": false,
    "do_objectID": "660A5B3B-26AD-414E-9D43-8828CD50F1BB",
    "height": 512,
    "width": 512,
    "x": 6884,
    "y": -1857
  },
  "hasBackgroundColor": false,
  "hasClickThrough": true,
  "hasClippingMask": false,
  "horizontalRulerData": {
    "_class": "rulerData",
    "base": 0,
    "do_objectID": "E9125C48-D1FC-4C6A-BE11-0D55F4D08D5A",
    "guides": [
    ]
  },
  "includeBackgroundColorInExport": true,
  "includeBackgroundColorInInstance": false,
  "includeInCloudUpload": true,
  "isFixedToViewport": false,
  "isFlippedHorizontal": false,
  "isFlippedVertical": false,
  "isFlowHome": false,
  "isLocked": false,
  "isVisible": true,
  "layerListExpandedType": 0,
  "layers": [
    {
      "class": "shapePath",
      "id": "83D48D36-0D78-4947-B672-E54DB0C04A86"
    },
    {
      "class": "symbolInstance",
      "id": "9AD93719-9846-487B-BA25-30A63A51E051"
    }
  ],
  "name": " md-resize",
  "nameIsFixed": true,
  "resizesContent": false,
  "resizingConstraint": 63,
  "resizingType": 0,
  "rotation": 0,
  "shouldBreakMaskChain": true,
  "style": {
    "_class": "style",
    "do_objectID": "63405C49-24DD-4B21-981F-AAA4E907BAB6",
    "endMarkerType": 0,
    "miterLimit": 10,
    "startMarkerType": 0,
    "windingRule": 1
  },
  "symbolID": "E42943D0-D6B0-4FDE-8D5F-D9E0777E1AFF",
  "userInfo": {
    "com.animaapp.stc-sketch-plugin": {
      "kModelPropertiesKey": {
      }
    }
  },
  "verticalRulerData": {
    "_class": "rulerData",
    "base": 0,
    "do_objectID": "23FF8733-B5C0-4A0A-812F-AE8E1781DFC7",
    "guides": [
    ]
  }
}