{
  "_class": "shapePath",
  "booleanOperation": -1,
  "clippingMaskMode": 0,
  "do_objectID": "7C01E1D5-C756-4F47-9A80-65E379D6F6B3",
  "edited": true,
  "exportOptions": {
    "_class": "exportOptions",
    "exportFormats": [
    ],
    "includedLayerIds": [
    ],
    "layerOptions": 0,
    "shouldTrim": false
  },
  "frame": {
    "_class": "rect",
    "constrainProportions": true,
    "height": 415.8999938964844,
    "width": 407.9999940124204,
    "x": 52,
    "y": 48
  },
  "hasClippingMask": true,
  "isClosed": true,
  "isFixedToViewport": false,
  "isFlippedHorizontal": false,
  "isFlippedVertical": false,
  "isLocked": false,
  "isVisible": true,
  "layerListExpandedType": 0,
  "name": "Mask",
  "nameIsFixed": false,
  "pointRadiusBehaviour": 1,
  "points": [
    {
      "_class": "curvePoint",
      "cornerRadius": 0,
      "curveFrom": "{0.99411764705882355, 0.42293820629959128}",
      "curveMode": 4,
      "curveTo": "{0.99436274509803924, 0.42438086078384224}",
      "hasCurveFrom": false,
      "hasCurveTo": true,
      "point": "{0.99411764705882355, 0.42293820629959128}"
    },
    {
      "_class": "curvePoint",
      "cornerRadius": 0,
      "curveFrom": "{0.98897058823529416, 0.40153883144986774}",
      "curveMode": 1,
      "curveTo": "{0.98897058823529416, 0.40153883144986774}",
      "hasCurveFrom": false,
      "hasCurveTo": false,
      "point": "{0.98897058823529416, 0.40153883144986774}"
    },
    {
      "_class": "curvePoint",
      "cornerRadius": 0,
      "curveFrom": "{0.51470588235294112, 0.40153883144986774}",
      "curveMode": 1,
      "curveTo": "{0.51470588235294112, 0.40153883144986774}",
      "hasCurveFrom": false,
      "hasCurveTo": false,
      "point": "{0.51470588235294112, 0.40153883144986774}"
    },
    {
      "_class": "curvePoint",
      "cornerRadius": 0,
      "curveFrom": "{0.51470588235294112, 0.59846116855013232}",
      "curveMode": 1,
      "curveTo": "{0.51470588235294112, 0.59846116855013232}",
      "hasCurveFrom": false,
      "hasCurveTo": false,
      "point": "{0.51470588235294112, 0.59846116855013232}"
    },
    {
      "_class": "curvePoint",
      "cornerRadius": 0,
      "curveFrom": "{0.7686274509803922, 0.73551334455397932}",
      "curveMode": 4,
      "curveTo": "{0.79803921568627456, 0.59846116855013232}",
      "hasCurveFrom": true,
      "hasCurveTo": false,
      "point": "{0.79803921568627456, 0.59846116855013232}"
    },
    {
      "_class": "curvePoint",
      "cornerRadius": 0,
      "curveFrom": "{0.43946078431372559, 0.80764606876653044}",
      "curveMode": 3,
      "curveTo": "{0.63210784313725499, 0.80764606876653044}",
      "hasCurveFrom": true,
      "hasCurveTo": true,
      "point": "{0.52058823529411768, 0.80764606876653044}"
    },
    {
      "_class": "curvePoint",
      "cornerRadius": 0,
      "curveFrom": "{0.23921568627450993, 0.66506371723972113}",
      "curveMode": 2,
      "curveTo": "{0.35392156862745106, 0.77422457321471516}",
      "hasCurveFrom": true,
      "hasCurveTo": true,
      "point": "{0.29730392156862756, 0.72036547246934357}"
    },
    {
      "_class": "curvePoint",
      "cornerRadius": 0,
      "curveFrom": "{0.20220588235294132, 0.41668670353450349}",
      "curveMode": 2,
      "curveTo": "{0.20220588235294132, 0.58355373887953843}",
      "hasCurveFrom": true,
      "hasCurveTo": true,
      "point": "{0.20220588235294132, 0.4996393363789372}"
    },
    {
      "_class": "curvePoint",
      "cornerRadius": 0,
      "curveFrom": "{0.3507352941176472, 0.22481365712911761}",
      "curveMode": 2,
      "curveTo": "{0.24019607843137269, 0.33373407069006972}",
      "hasCurveFrom": true,
      "hasCurveTo": true,
      "point": "{0.29558823529411776, 0.27915364270257276}"
    },
    {
      "_class": "curvePoint",
      "cornerRadius": 0,
      "curveFrom": "{0.61250000000000004, 0.19403702813176243}",
      "curveMode": 3,
      "curveTo": "{0.4343137254901962, 0.19403702813176243}",
      "hasCurveFrom": true,
      "hasCurveTo": true,
      "point": "{0.51740196078431377, 0.19403702813176243}"
    },
    {
      "_class": "curvePoint",
      "cornerRadius": 0,
      "curveFrom": "{0.7061274509803922, 0.2661697523443135}",
      "curveMode": 4,
      "curveTo": "{0.68063725490196092, 0.24356816542438084}",
      "hasCurveFrom": false,
      "hasCurveTo": true,
      "point": "{0.7061274509803922, 0.2661697523443135}"
    },
    {
      "_class": "curvePoint",
      "cornerRadius": 0,
      "curveFrom": "{0.80686274509803924, 0.090887232507814358}",
      "curveMode": 4,
      "curveTo": "{0.84877450980392155, 0.12695359461408992}",
      "hasCurveFrom": true,
      "hasCurveTo": false,
      "point": "{0.84877450980392155, 0.12695359461408992}"
    },
    {
      "_class": "curvePoint",
      "cornerRadius": 0,
      "curveFrom": "{0.37450980392156874, 0}",
      "curveMode": 3,
      "curveTo": "{0.69191176470588234, 0}",
      "hasCurveFrom": true,
      "hasCurveTo": true,
      "point": "{0.51274509803921575, 0}"
    },
    {
      "_class": "curvePoint",
      "cornerRadius": 0,
      "curveFrom": "{0.049509803921568632, 0.23996152921375336}",
      "curveMode": 2,
      "curveTo": "{0.24191176470588246, 0.051935561433036806}",
      "hasCurveFrom": true,
      "hasCurveTo": true,
      "point": "{0.1450980392156864, 0.14666987256552055}"
    },
    {
      "_class": "curvePoint",
      "cornerRadius": 0,
      "curveFrom": "{0, 0.62490983409473433}",
      "curveMode": 2,
      "curveTo": "{0, 0.37484972349122392}",
      "hasCurveFrom": true,
      "hasCurveTo": true,
      "point": "{0, 0.49987977879297912}"
    },
    {
      "_class": "curvePoint",
      "cornerRadius": 0,
      "curveFrom": "{0.23848039215686279, 0.94758355373887948}",
      "curveMode": 2,
      "curveTo": "{0.046813725490196065, 0.75330608319307524}",
      "hasCurveFrom": true,
      "hasCurveTo": true,
      "point": "{0.13946078431372549, 0.84731906708343352}"
    },
    {
      "_class": "curvePoint",
      "cornerRadius": 0,
      "curveFrom": "{0.65441176470588236, 1}",
      "curveMode": 3,
      "curveTo": "{0.37867647058823528, 1}",
      "hasCurveFrom": true,
      "hasCurveTo": true,
      "point": "{0.52303921568627443, 1}"
    },
    {
      "_class": "curvePoint",
      "cornerRadius": 0,
      "curveFrom": "{0.95490196078431377, 0.7677326280355854}",
      "curveMode": 2,
      "curveTo": "{0.77892156862745088, 0.94950709305121428}",
      "hasCurveFrom": true,
      "hasCurveTo": true,
      "point": "{0.86764705882352944, 0.8578985333012743}"
    },
    {
      "_class": "curvePoint",
      "cornerRadius": 0,
      "curveFrom": "{1, 0.45708102909353199}",
      "curveMode": 3,
      "curveTo": "{1, 0.64294301514787211}",
      "hasCurveFrom": true,
      "hasCurveTo": true,
      "point": "{1, 0.51214234190911267}"
    }
  ],
  "resizingConstraint": 63,
  "resizingType": 0,
  "rotation": 0,
  "shouldBreakMaskChain": false,
  "style": {
    "_class": "style",
    "do_objectID": "C3A87835-F92D-46F8-BCD2-C509B0E1D4AC",
    "endMarkerType": 0,
    "fills": [
      {
        "_class": "fill",
        "color": {
          "_class": "color",
          "alpha": 1,
          "blue": 0,
          "green": 0,
          "red": 0
        },
        "fillType": 0,
        "isEnabled": true,
        "noiseIndex": 0,
        "noiseIntensity": 0,
        "patternFillType": 1,
        "patternTileScale": 1
      }
    ],
    "miterLimit": 10,
    "startMarkerType": 0,
    "windingRule": 0
  },
  "userInfo": {
    "com.animaapp.stc-sketch-plugin": {
      "kModelPropertiesKey": {
        "constraints": {
          "aspectRatio": {
            "constant": 415.9,
            "enabled": 1,
            "modelID": "constraint_c3f753d5-a744-4632-aab8-845cc5845585",
            "model_class": "ADModelConstraint",
            "model_version": 0.1,
            "multiplier": 408
          },
          "automatic": 1,
          "modelID": "viewConstraints_6f22ee36-1dcd-4b4f-a09f-3da057fac718",
          "model_class": "ADModelViewConstraints",
          "model_version": 0.1,
          "scaleFactor": 1
        }
      }
    }
  }
}