{
  "_class": "group",
  "booleanOperation": 0,
  "clippingMaskMode": 0,
  "do_objectID": "9424B48B-CFD1-41E1-AF90-3663D3958943",
  "exportOptions": {
    "_class": "exportOptions",
    "exportFormats": [
    ],
    "includedLayerIds": [
    ],
    "layerOptions": 0,
    "shouldTrim": false
  },
  "frame": {
    "_class": "rect",
    "constrainProportions": false,
    "height": 168,
    "width": 17,
    "x": 8,
    "y": -1
  },
  "hasClickThrough": false,
  "hasClippingMask": false,
  "isFixedToViewport": false,
  "isFlippedHorizontal": false,
  "isFlippedVertical": false,
  "isLocked": false,
  "isVisible": true,
  "layerListExpandedType": 0,
  "layers": [
    {
      "class": "text",
      "id": "69985FE0-8D37-4A6F-B0BB-CCE82E214B90"
    },
    {
      "class": "text",
      "id": "55A28369-6967-4A56-98D2-CFA94A9DE692"
    },
    {
      "class": "text",
      "id": "1E48B8B9-E746-49C5-A952-7F32B6672F3E"
    },
    {
      "class": "text",
      "id": "3313491D-C63B-4699-A677-5F0F2144587F"
    },
    {
      "class": "text",
      "id": "5B8BD2FC-8500-4A4F-A717-324E8E104206"
    },
    {
      "class": "text",
      "id": "350BF409-42A9-4C44-A9D5-68CB09DF466A"
    },
    {
      "class": "text",
      "id": "BA5A15A9-B08A-43E6-A61D-1306F62ADDB9"
    },
    {
      "class": "text",
      "id": "C5F1A770-E80A-4A95-9750-0082500EEC96"
    }
  ],
  "name": "element/graphe/L-absis",
  "nameIsFixed": true,
  "resizingConstraint": 59,
  "resizingType": 0,
  "rotation": 0,
  "shouldBreakMaskChain": false,
  "style": {
    "_class": "style",
    "endMarkerType": 0,
    "miterLimit": 10,
    "startMarkerType": 0,
    "windingRule": 1
  },
  "userInfo": {
    "com.animaapp.stc-sketch-plugin": {
      "kModelPropertiesKey": {
        "align": 3,
        "isCollapsing": 1,
        "spacing": 8,
        "stackType": 0
      },
      "kViewTypeKey": "ADModelStackView"
    }
  }
}